<annotation>
	<folder>geometry_annotation</folder>
	<filename>1735.png</filename>
	<source>
		<database>Unknown</database>
	</source>
	<size>
		<width>393</width>
		<height>246</height>
		<depth>3</depth>
	</size>
	<segmented>0</segmented>
	<object>
		<name>text</name>
		<pose>Unspecified</pose>
		<truncated>0</truncated>
		<difficult>0</difficult>
		<bndbox>
			<xmin>17</xmin>
			<ymin>18</ymin>
			<xmax>42</xmax>
			<ymax>48</ymax>
		</bndbox>
	</object>
	<object>
		<name>text</name>
		<pose>Unspecified</pose>
		<truncated>0</truncated>
		<difficult>0</difficult>
		<bndbox>
			<xmin>18</xmin>
			<ymin>193</ymin>
			<xmax>50</xmax>
			<ymax>219</ymax>
		</bndbox>
	</object>
	<object>
		<name>text</name>
		<pose>Unspecified</pose>
		<truncated>0</truncated>
		<difficult>0</difficult>
		<bndbox>
			<xmin>171</xmin>
			<ymin>136</ymin>
			<xmax>196</xmax>
			<ymax>162</ymax>
		</bndbox>
	</object>
	<object>
		<name>text</name>
		<pose>Unspecified</pose>
		<truncated>0</truncated>
		<difficult>0</difficult>
		<bndbox>
			<xmin>323</xmin>
			<ymin>193</ymin>
			<xmax>349</xmax>
			<ymax>221</ymax>
		</bndbox>
	</object>
	<object>
		<name>perpendicular</name>
		<pose>Unspecified</pose>
		<truncated>0</truncated>
		<difficult>0</difficult>
		<bndbox>
			<xmin>40</xmin>
			<ymin>163</ymin>
			<xmax>72</xmax>
			<ymax>192</ymax>
		</bndbox>
	</object>
	<object>
		<name>text</name>
		<pose>Unspecified</pose>
		<truncated>0</truncated>
		<difficult>0</difficult>
		<bndbox>
			<xmin>326</xmin>
			<ymin>21</ymin>
			<xmax>347</xmax>
			<ymax>52</ymax>
		</bndbox>
	</object>
</annotation>