<annotation>
	<folder>geometry_annotation</folder>
	<filename>1890.png</filename>
	<source>
		<database>Unknown</database>
	</source>
	<size>
		<width>556</width>
		<height>525</height>
		<depth>3</depth>
	</size>
	<segmented>0</segmented>
	<object>
		<name>text</name>
		<pose>Unspecified</pose>
		<truncated>0</truncated>
		<difficult>0</difficult>
		<bndbox>
			<xmin>281</xmin>
			<ymin>79</ymin>
			<xmax>324</xmax>
			<ymax>123</ymax>
		</bndbox>
	</object>
	<object>
		<name>text</name>
		<pose>Unspecified</pose>
		<truncated>0</truncated>
		<difficult>0</difficult>
		<bndbox>
			<xmin>410</xmin>
			<ymin>107</ymin>
			<xmax>456</xmax>
			<ymax>152</ymax>
		</bndbox>
	</object>
	<object>
		<name>text</name>
		<pose>Unspecified</pose>
		<truncated>0</truncated>
		<difficult>0</difficult>
		<bndbox>
			<xmin>211</xmin>
			<ymin>131</ymin>
			<xmax>276</xmax>
			<ymax>174</ymax>
		</bndbox>
	</object>
	<object>
		<name>text</name>
		<pose>Unspecified</pose>
		<truncated>0</truncated>
		<difficult>0</difficult>
		<bndbox>
			<xmin>178</xmin>
			<ymin>398</ymin>
			<xmax>220</xmax>
			<ymax>444</ymax>
		</bndbox>
	</object>
	<object>
		<name>text</name>
		<pose>Unspecified</pose>
		<truncated>0</truncated>
		<difficult>0</difficult>
		<bndbox>
			<xmin>346</xmin>
			<ymin>368</ymin>
			<xmax>383</xmax>
			<ymax>411</ymax>
		</bndbox>
	</object>
</annotation>